sglnbgrader/__init__.py
sglnbgrader/__main__.py
sglnbgrader/cli.py
sglnbgrader/grader.py
sglnbgrader-0.1.0.dist-info/METADATA
sglnbgrader-0.1.0.dist-info/WHEEL
sglnbgrader-0.1.0.dist-info/entry_points.txt
sglnbgrader-0.1.0.dist-info/top_level.txt
sglnbgrader-0.1.0.dist-info/RECORD
