Metadata-Version: 2.4
Name: sglnbgrader
Version: 0.1.0
Summary: LLM-powered Jupyter notebook grading tool with nbgrader compatibility
Requires-Python: >=3.12
Requires-Dist: litellm>=1.67.4.post1
Requires-Dist: nbformat>=5.10.4
Requires-Dist: openai>=1.76.0
Requires-Dist: pytest>=8.3.5
Requires-Dist: pytest-mock>=3.14.0
Requires-Dist: rich>=14.0.0
Requires-Dist: typer>=0.15.2
Requires-Dist: numpy>=1.26.0
